escli/VERSION
escli/__init__.py
escli/__main__.py
escli/io.py
escli/version.py
escli/commands/__init__.py
escli/commands/formats.py
escli/commands/indexes.py
escli/commands/ingest.py
escli/commands/search.py
escli/commands/version.py
escli/services/__init__.py
escli/services/elasticsearch.py
escli/services/enterprisesearch.py
escli-2021.0.dev7.dist-info/LICENSE.md
escli-2021.0.dev7.dist-info/METADATA
escli-2021.0.dev7.dist-info/NOTICE.md
escli-2021.0.dev7.dist-info/WHEEL
escli-2021.0.dev7.dist-info/entry_points.txt
escli-2021.0.dev7.dist-info/top_level.txt
escli-2021.0.dev7.dist-info/RECORD
