Metadata-Version: 2.1
Name: escli
Version: 2021.0.dev7
Summary: UNKNOWN
Home-page: https://github.com/technige/escli
Author: Nigel Small
Author-email: nigel.small@elastic.co
License: Apache-2.0
Platform: UNKNOWN
Requires-Python: >=3.6
License-File: LICENSE.md
License-File: NOTICE.md
Requires-Dist: elasticsearch
Requires-Dist: tabulate
